cluster_funk/__init__.py
cluster_funk/bootstrap.py
cluster_funk/main.py
cluster_funk/controllers/__init__.py
cluster_funk/controllers/arguments.py
cluster_funk/controllers/base.py
cluster_funk/controllers/clusters.py
cluster_funk/controllers/environments.py
cluster_funk/controllers/jobs.py
cluster_funk/controllers/user_id.py
cluster_funk/core/__init__.py
cluster_funk/core/exc.py
cluster_funk/core/utils.py
cluster_funk/core/version.py
cluster_funk/core/clusters/__init__.py
cluster_funk/core/clusters/cluster_booter.py
cluster_funk/core/clusters/cluster_instance.py
cluster_funk/core/clusters/cluster_instance_collection.py
cluster_funk/core/clusters/emr_cluster.py
cluster_funk/core/environments/__init__.py
cluster_funk/core/environments/stack_collection.py
cluster_funk/core/environments/stack_deployer.py
cluster_funk/core/jobs/__init__.py
cluster_funk/core/jobs/job_collection.py
cluster_funk/core/notebooks/__init__.py
cluster_funk/core/notebooks/sagemaker_notebook_booter.py
cluster_funk/ext/__init__.py
cluster_funk/plugins/__init__.py
cluster_funk/templates/__init__.py
cluster_funk/templates/base/README.md
cluster_funk/templates/base/.cf/.keep
cluster_funk/templates/base/environments/dev/iam.yml
cluster_funk/templates/base/environments/dev/vpc.yml
cluster_funk/templates/base/environments/prd/iam.yml
cluster_funk/templates/base/environments/prd/vpc.yml
cluster_funk/templates/base/environments/stg/iam.yml
cluster_funk/templates/base/environments/stg/vpc.yml
cluster_funk/templates/base/jobs/.keep
cluster_funk/templates/word_count/README.md
cluster_funk/templates/word_count/main.py
cluster_funk/templates/word_count/requirements-dev.txt
cluster_funk/templates/word_count/tests/__init__.py
cluster_funk/templates/word_count/tests/fixtures/words.txt
cluster_funk-0.0.2a14.dist-info/LICENSE
cluster_funk-0.0.2a14.dist-info/LICENSE.md
cluster_funk-0.0.2a14.dist-info/METADATA
cluster_funk-0.0.2a14.dist-info/WHEEL
cluster_funk-0.0.2a14.dist-info/entry_points.txt
cluster_funk-0.0.2a14.dist-info/top_level.txt
cluster_funk-0.0.2a14.dist-info/RECORD
