Metadata-Version: 2.1
Name: cluster-funk
Version: 0.0.2a14
Summary: CLI for managing EMR clusters for big data
Home-page: https://bitbucket.org/jeffdurand/cluster_funk
Author: Jeff Durand
Author-email: jeff.durand@gmail.com
License: unlicensed
Platform: UNKNOWN
Requires-Dist: tinydb
Requires-Dist: boto3
Requires-Dist: colorlog
Requires-Dist: jinja2
Requires-Dist: pyyaml
Requires-Dist: fabric
